README.md
setup.py
jupyterlab_black/__init__.py
jupyterlab_black/handlers.py
jupyterlab_black.egg-info/PKG-INFO
jupyterlab_black.egg-info/SOURCES.txt
jupyterlab_black.egg-info/dependency_links.txt
jupyterlab_black.egg-info/requires.txt
jupyterlab_black.egg-info/top_level.txt