Metadata-Version: 1.0
Name: jupyterlab-black
Version: 0.2.1
Summary: The server extension for jupyterlab_black, to apply the black formatter to codecell content.
Home-page: https://github.com/ryantam626/jupyterlab_black
Author: Ryan Tam
Author-email: ryantam626@gmail.com
License: MIT
Platform: UNKNOWN
